family_ai_voice_assistant/__init__.py
family_ai_voice_assistant/basic_entry.py
family_ai_voice_assistant/impl/chat_session_clients/__init__.py
family_ai_voice_assistant/impl/chat_session_clients/open_ai_style_chat_session.py
family_ai_voice_assistant/impl/configs/__init__.py
family_ai_voice_assistant/impl/configs/azure_open_ai_config.py
family_ai_voice_assistant/impl/configs/azure_speech_config.py
family_ai_voice_assistant/impl/configs/coqui_tts_config.py
family_ai_voice_assistant/impl/configs/ollama_config.py
family_ai_voice_assistant/impl/configs/open_ai_config.py
family_ai_voice_assistant/impl/configs/openai_whisper_config.py
family_ai_voice_assistant/impl/configs/picovoice_config.py
family_ai_voice_assistant/impl/configs/snowboy_config.py
family_ai_voice_assistant/impl/llm_clients/__init__.py
family_ai_voice_assistant/impl/llm_clients/azure_open_ai.py
family_ai_voice_assistant/impl/llm_clients/ollama.py
family_ai_voice_assistant/impl/llm_clients/open_ai.py
family_ai_voice_assistant/impl/llm_clients/open_ai_base.py
family_ai_voice_assistant/impl/resources/snowboy/common.res
family_ai_voice_assistant/impl/resources/snowboy/models/snowboy.umdl
family_ai_voice_assistant/impl/speech_to_text/__init__.py
family_ai_voice_assistant/impl/speech_to_text/recognition_clients/__init__.py
family_ai_voice_assistant/impl/speech_to_text/recognition_clients/azure_recognition.py
family_ai_voice_assistant/impl/speech_to_text/recognition_clients/openai_whisper.py
family_ai_voice_assistant/impl/speech_to_text/waker_clients/__init__.py
family_ai_voice_assistant/impl/speech_to_text/waker_clients/_snowboy/__init__.py
family_ai_voice_assistant/impl/speech_to_text/waker_clients/_snowboy/amd64/__init__.py
family_ai_voice_assistant/impl/speech_to_text/waker_clients/_snowboy/amd64/_snowboydetect.so
family_ai_voice_assistant/impl/speech_to_text/waker_clients/_snowboy/arm64/_snowboydetect.so
family_ai_voice_assistant/impl/speech_to_text/waker_clients/_snowboy/snowboydecoder.py
family_ai_voice_assistant_impl-0.1.0.dist-info/METADATA
family_ai_voice_assistant_impl-0.1.0.dist-info/WHEEL
family_ai_voice_assistant_impl-0.1.0.dist-info/entry_points.txt
family_ai_voice_assistant_impl-0.1.0.dist-info/RECORD
